{
  "schema": 1,
  "project": {
    "name": "balu",
    "description": "# Plano de 4 Dias — Balu v1\n\nRoteiro executável para entregar a v1 do Balu em 4 dias úteis. Stack: **Next.js 15 + Supabase + Tailwind**. Cada PR sugerido = 1 unidade lógica que vira 1 pull request. Cadência de review: pausar para aprovação a cada PR.\n\nFonte detalhada: `PLANO-4-DIAS.md`. Specs por feature: `V1-FUNCIONALIDADES.md`. O que reusar: `STATUS-IMPLEMENTACAO.md`.",
    "epic_metadata": {
      "Resumo do épico": "- **Day 1**: Dashboard + Notas (listagem/detalhe/cancelamento)\n- **Day 2**: Emissão de NFS-e (sandbox Focus)\n- **Day 3**: Apuração de impostos + geração de DAS (sandbox Serpro) + cron mensal\n- **Day 4**: Testes E2E + polish de UX + handoff\n\nTotal: 5 rotas, 6+ server actions, 4+ componentes, 1 cron, 1 webhook ampliado.",
      "Out of scope (vão pra v2)": "WhatsApp, IA conversacional, busca semântica, conciliação bancária, domínio personalizado, IA tradutor leigo. Detalhe em `V2-FUNCIONALIDADES.md`."
    },
    "integrations": {
      "trello": {
        "boardId": "6a1461ca434516b0eb7bd20c",
        "listMap": {
          "todo": "6a1461cb8f82f6b2f5e49108",
          "in_progress": "6a1461cbeb16516cc885c944",
          "blocked": "6a1461cb5e9e3919047c23d8",
          "review": "6a1461cc2ccb91915d1a9f15",
          "done": "6a1461cccb180cd861e73055"
        },
        "cardMap": {
          "1ab181d6-3e5a-4e39-98fc-575761b529e0": "6a1461d0f777e8410dd4a0f8",
          "0326546a-c1f3-453f-bc6b-e3bb774e9151": "6a1461d42d52b5f6bd7a6b57",
          "60b2749c-997b-4b68-a730-175dc0f0284e": "6a1461d717046490db6571b5",
          "0218026a-9e84-4cf1-bb96-78cc165b9e20": "6a1461dbb4dff4b40cd76041",
          "f7db9186-a612-417a-ba03-2c6926d4d45f": "6a1461e0438306285a17ddd4",
          "44d55ef0-1b25-4a40-bea4-8f50ee5b09f7": "6a1461e39e8ba98e84052c50",
          "ecf53346-6f3c-492d-a3e2-31e35066acf8": "6a1461e7c60400828c5dda6d",
          "4a1af89a-ccea-4596-bfc9-700864a15caa": "6a1461ea1aa9b1554f18fa8f",
          "4bc34186-3487-4731-a4d1-0d5011d803e4": "6a1461eeff223671a9a46ca0",
          "d09e237d-2168-4f6f-8a2a-4e86535dd291": "6a1461f276e270ce3f1a6193",
          "45017bed-aa05-4aea-9c43-362692a8f0c3": "6a1461f6893761004741f22d",
          "f96857de-5f7c-4620-97a1-79a3f96163e1": "6a1461f987e07ae9d17c86f8",
          "cd6a6b8e-4aac-417c-951a-7eaa53f5f433": "6a15f2bc7644870295f60a02",
          "2a06f614-49f1-4669-94e5-2620f26370df": "6a15f2eeeef369d07e6aa248",
          "e87f3040-755d-41ee-a2db-8033efdb8335": "6a15f2f2f3da44317fc00277"
        },
        "labelMap": {
          "priority: high::red": "6a1461cfd9a131398530abb8",
          "day1::blue": "6a1461cf71836ddfec96659d",
          "dashboard::blue": "6a1461d0ba594501aa9e3332",
          "notas::blue": "6a1461d3bb4e8a46dfad1ea7",
          "day2::blue": "6a1461db68b038b4a6103322",
          "emissao::blue": "6a1461dbe49ebdac0a8687c9",
          "priority: medium::yellow": "6a1461df4ad084ea66f1687e",
          "day3::blue": "6a1461e28f82f6b2f5e4e022",
          "impostos::blue": "6a1461e31aa3e6197289f17d",
          "wizard::blue": "6a1461e7d14181fc98dd5028",
          "cron::blue": "6a1461ea9e8ba98e84054e4d",
          "day4::blue": "6a1461ed364768d049c6a8ba",
          "tests::blue": "6a1461ed216c724aa991a0f7",
          "e2e::blue": "6a1461ee8c0f71c75d252b5d",
          "ux::blue": "6a1461f13435cc664445a39b",
          "polish::blue": "6a1461f203f186bd6137af08",
          "priority: low::green": "6a1461f5b762958e31f05e3c",
          "docs::blue": "6a1461f5d6ad0a8d473c4e69",
          "handoff::blue": "6a1461f9f43122e9f92c88eb",
          "revisão::blue": "6a14b57aaccefc06373d3a83",
          "qa::blue": "6a14b57b8c2e212e63144f32",
          "prioridade-máxima::blue": "6a14b57b53c4500ec989f5d1",
          "auth::blue": "6a14b5a82e4a4a512b4dc8bf",
          "cadastro::blue": "6a14b5a99c5fe5cdaacfc249",
          "db::blue": "6a15f2f140b8495ad996dce1",
          "reconciliação::blue": "6a15f2f116be8878b841ef2b"
        }
      }
    }
  },
  "columns": [
    {
      "id": "todo",
      "title": "To Do"
    },
    {
      "id": "in_progress",
      "title": "In Progress"
    },
    {
      "id": "blocked",
      "title": "Blocked"
    },
    {
      "id": "review",
      "title": "Review"
    },
    {
      "id": "done",
      "title": "Done"
    }
  ],
  "cards": [
    {
      "id": "cd6a6b8e-4aac-417c-951a-7eaa53f5f433",
      "title": "Revisão Balu",
      "status": "in_progress",
      "priority": "high",
      "estimate": "M (4-6h)",
      "labels": [
        "revisão",
        "qa",
        "prioridade-máxima"
      ],
      "dependencies": [
        "PR 1.1",
        "PR 1.2"
      ],
      "description": "## ✅ ACHADO CRÍTICO — RESOLVIDO (2026-05-26)\nDecisão: **banco = fonte da verdade**. Reconciliado e validado E2E no browser.\n- Diagnóstico completo: `DB-DIVERGENCIA.md` (raiz)\n- `8929d2c` — Passo 0+1: types regen do banco real + dashboard/notas alinhados\n- `92e12fd` — Passo 1.5: auth/onboarding/profile (status, .eq(user_id), user_role, RPC)\n\n### Verificação runtime 2026-05-26 (Playwright, conta allanvalle@outlook.com)\n✅ Cadastro · ✅ Onboarding/criar empresa · ✅ Dashboard (vazio + com dados R$250) · ✅ Notas listagem (cliente via payload, status, ordem) · ✅ Clientes criar+listar · ✅ tsc verde\nPendente: login form submit, troca de empresa, editar/excluir cliente, filtros+CSV de notas, detalhe/cancelamento (PR 1.3), lookup CNPJ Focus/CEP, next build, Playwright suite.\nScreenshots: `balu-next/screenshots/verify/`.\n\n---\n**Prioridade máxima.** Antes de retomar o desenvolvimento, fazer um passe de QA de **tudo que já existe** no app. Boa parte foi verificada só em `tsc`/`next build` — falta a verificação de **runtime com Supabase real** (criar `.env.local`). Referência do que está pronto: `STATUS-IMPLEMENTACAO.md` §2 e §3.\n\nAuth:\n- [ ] Login com credenciais válidas entra no dashboard\n- [ ] Cadastro cria usuário + profile (trigger `handle_new_user`)\n- [ ] Reset de senha: request + update via `?code=`\n- [ ] Rotas protegidas redirecionam para `/login` sem sessão\n\nEmpresa / onboarding:\n- [ ] Criar empresa no onboarding (lookup CNPJ Focus + CEP ViaCEP)\n- [ ] Troca de empresa ativa no `<MenuLateral>`\n- [ ] Editar dados da empresa em `/configuracoes`\n\nClientes:\n- [ ] Criar cliente (dedup CPF/CNPJ rejeita duplicado)\n- [ ] Editar cliente\n- [ ] Excluir (soft delete) cliente\n- [ ] Listagem com busca/filtros\n\nDashboard (PR 1.1):\n- [ ] 4 cards mostram dados reais (não placeholder)\n- [ ] Lista \"O que você precisa fazer\" carrega de dados reais\n- [ ] Botão \"Pagar\" abre `<PagarGuiaModal>` (stub)\n\nListagem de notas (PR 1.2):\n- [ ] Lista ordenada por `data_emissao desc`\n- [ ] 4 filtros combináveis funcionam\n- [ ] Export CSV baixa arquivo válido\n- [ ] Linha clicável navega para `/notas_fiscais/<id>`\n\nQualidade / infra:\n- [ ] `tsc --noEmit` zero erros\n- [ ] `next build` sucesso\n- [ ] Playwright smoke + walkthrough passando\n- [ ] Runtime validado contra Supabase real (`.env.local` configurado)\n\n---\n## 🔴 ACHADO CRÍTICO (revisão runtime 2026-05-25)\nO banco Supabase do `.env.local` (projeto `llykzqnugdpojwnlontj`, origem Bubble) **não corresponde** à migration `0001_init.sql`. O código foi escrito contra a migration; o banco real tem o schema do Bubble. Incompatível em quase todas as tabelas:\n- `companies`: faltam `status`, `bubble_id` → **criar empresa falha** (PGRST204 status; o código ainda manda `status:'ativa'`, valor fora do CHECK active|inactive).\n- `notas_fiscais`: live tem `tipo_documento/referencia/payload_focusnfe`; faltam `cliente_id, tipo_nf, ref, chave_acesso, xml_url, pdf_url, focus_response...`.\n- `apuracoes_fiscais` e `guias_fiscais`: usam `company_id` (não `empresa_id`), nomes totalmente diferentes.\n- `municipios_nfse`, `abertura_empresas`: schemas divergentes.\n- `aux_produtos` e `declaracoes_fiscais`: **não existem** no banco (404).\n- Keys: ANON é novo formato (`sb_publishable_`), service_role é JWT legado — endpoint swagger exige `sb_secret_`.\n\n**Impacto:** dashboard, notas, impostos — tudo que toca essas tabelas falha em runtime. Migration nunca foi aplicada neste projeto.\n**Próximo:** reconciliar schema (aplicar 0001_init.sql em projeto limpo) antes de continuar a revisão de runtime.\n\n---\n## ✅ 2º passe de QA runtime (2026-05-26, Playwright)\nFechados: login, reset (solicitação), troca de empresa, editar empresa, criar/editar/excluir cliente, dashboard c/ dados (R$250 + guia R$1.320 + pendências), notas (filtros combináveis, CSV válido, linha→detalhe), next build OK.\n\n**Pendências (2 itens não marcados):**\n- 🟡 **Botão 'Pagar'**: é um link para `/impostos` (stub), NÃO abre `<PagarGuiaModal>` — desvio do DoD do plano.\n- 🔴 **Playwright smoke+walkthrough**: 8/18 passam. As 10 falhas são por **hydration mismatch do React** (SSR≠client) presente em TODAS as páginas (incl. /login, que não foi alterado) → **pré-existente e global**, não regressão do Passo 0/1/1.5. Investigar à parte.\n\n**Findings menores:** (1) campo E-mail do form de cliente acusa 'Invalid email' quando vazio, apesar de opcional → bloqueia cadastro sem email; (2) reset via `?code=` não testável sem o link do e-mail; (3) lookup CNPJ Focus não retornou dados (sandbox).\n\n---\n## ✅ Hydration investigado + Playwright 18/18 (2026-05-26)\nRoot cause das 10 falhas: **não era bug de markup**, e sim ruído do `next dev` (Fast Refresh + hydration por compilação sob demanda) batendo no assert de 'zero erro no console'. Contra `next build && next start` passam todas. Fixes (commit 19d56a7): webServer no playwright.config (roda contra produção) + locator de senha por `name` (o smoke casava 2 inputs após o campo de confirmação). **`npx playwright test → 18/18`.**\nResta 1 item: 🟡 Botão 'Pagar' (link p/ /impostos vs `<PagarGuiaModal>`) — decisão de produto.",
      "checklist": [
        {
          "text": "Login com credenciais válidas entra no dashboard",
          "checked": true
        },
        {
          "text": "Cadastro cria usuário + profile (trigger `handle_new_user`)",
          "checked": true
        },
        {
          "text": "Reset de senha: request + update via `?code=`",
          "checked": true
        },
        {
          "text": "Rotas protegidas redirecionam para `/login` sem sessão",
          "checked": true
        },
        {
          "text": "Criar empresa no onboarding (lookup CNPJ Focus + CEP ViaCEP)",
          "checked": true
        },
        {
          "text": "Troca de empresa ativa no `<MenuLateral>`",
          "checked": true
        },
        {
          "text": "Editar dados da empresa em `/configuracoes`",
          "checked": true
        },
        {
          "text": "Criar cliente (dedup CPF/CNPJ rejeita duplicado)",
          "checked": true
        },
        {
          "text": "Editar cliente",
          "checked": true
        },
        {
          "text": "Excluir (soft delete) cliente",
          "checked": true
        },
        {
          "text": "Listagem com busca/filtros",
          "checked": true
        },
        {
          "text": "4 cards mostram dados reais (não placeholder)",
          "checked": true
        },
        {
          "text": "Lista \"O que você precisa fazer\" carrega de dados reais",
          "checked": true
        },
        {
          "text": "Botão \"Pagar\" abre `<PagarGuiaModal>` (stub)",
          "checked": false
        },
        {
          "text": "Lista ordenada por `data_emissao desc`",
          "checked": true
        },
        {
          "text": "4 filtros combináveis funcionam",
          "checked": true
        },
        {
          "text": "Export CSV baixa arquivo válido",
          "checked": true
        },
        {
          "text": "Linha clicável navega para `/notas_fiscais/<id>`",
          "checked": true
        },
        {
          "text": "`tsc --noEmit` zero erros",
          "checked": true
        },
        {
          "text": "`next build` sucesso",
          "checked": true
        },
        {
          "text": "Playwright smoke + walkthrough passando",
          "checked": true
        },
        {
          "text": "Runtime validado contra Supabase real (`.env.local` configurado)",
          "checked": true
        }
      ],
      "createdAt": "2026-05-25T14:56:03.642838+00:00",
      "updatedAt": "2026-05-26T20:00:32.000Z",
      "order": 0
    },
    {
      "id": "1ab181d6-3e5a-4e39-98fc-575761b529e0",
      "title": "PR 1.1: Dashboard home (`/`)",
      "status": "done",
      "priority": "high",
      "estimate": "M (4-6h)",
      "labels": [
        "day1",
        "dashboard"
      ],
      "dependencies": [],
      "description": "✅ FEITO (commit `9d0461f`, código; runtime pendente Supabase). Spec: `V1-FUNCIONALIDADES.md` §5.1 + §5.2.\n\nServer component com 4 queries em paralelo: receita do mês atual, próxima guia vencendo, última nota emitida, lista de pendências (notas em erro, guias vencendo em 7d, certificado A1 vencendo em 30d).\n\nArquivos: `app/(auth)/page.tsx`, `components/DashboardCard.tsx`, `components/PendingActionsList.tsx`, `lib/dashboard/queries.ts`. Reusa `<MenuLateral>`, `useToast()`, padrão de `clientes/page.tsx`.\n\nDoD:\n- [ ] `/` mostra 4 cards reais (não placeholder)\n- [ ] Card \"Próxima guia\" tem botão \"Pagar\" que abre `<PagarGuiaModal>` (stub OK por hoje)\n- [ ] Lista de pendências carrega de dados reais\n- [ ] `tsc --noEmit` zero erros",
      "checklist": [
        {
          "text": "`/` mostra 4 cards reais (não placeholder)",
          "checked": false
        },
        {
          "text": "Card \"Próxima guia\" tem botão \"Pagar\" que abre `<PagarGuiaModal>` (stub OK por hoje)",
          "checked": false
        },
        {
          "text": "Lista de pendências carrega de dados reais",
          "checked": false
        },
        {
          "text": "`tsc --noEmit` zero erros",
          "checked": false
        }
      ],
      "createdAt": "2026-05-25T14:48:34.226604+00:00",
      "updatedAt": "2026-05-25T14:56:19.802307+00:00",
      "order": 0
    },
    {
      "id": "0326546a-c1f3-453f-bc6b-e3bb774e9151",
      "title": "PR 1.2: Listagem de notas (`/notas_fiscais`)",
      "status": "done",
      "priority": "high",
      "estimate": "M (4-6h)",
      "labels": [
        "day1",
        "notas"
      ],
      "dependencies": [],
      "description": "✅ FEITO (commit `4fe1e80`, código; runtime pendente Supabase). Spec: `V1-FUNCIONALIDADES.md` §3.2.\n\nArquivos: `app/(auth)/notas_fiscais/page.tsx`, `notas_fiscais/NotasFiscaisList.tsx` (client), `notas_fiscais/actions.ts` (`exportNotasCsvAction`). Reusa `<FilterPeriodo>`, `<Toaster>`, padrão de `ClientesListClient.tsx`. Filtros: período, tipo (TipoNF), status, texto livre.\n\nDoD:\n- [ ] Lista 1 página (50 notas) ordenadas por `data_emissao desc`\n- [ ] 4 filtros funcionam (combináveis)\n- [ ] Export CSV baixa arquivo válido\n- [ ] Linha clicável navega para `/notas_fiscais/<id>`",
      "checklist": [
        {
          "text": "Lista 1 página (50 notas) ordenadas por `data_emissao desc`",
          "checked": false
        },
        {
          "text": "4 filtros funcionam (combináveis)",
          "checked": false
        },
        {
          "text": "Export CSV baixa arquivo válido",
          "checked": false
        },
        {
          "text": "Linha clicável navega para `/notas_fiscais/<id>`",
          "checked": false
        }
      ],
      "createdAt": "2026-05-25T14:48:34.226604+00:00",
      "updatedAt": "2026-05-25T14:56:19.802307+00:00",
      "order": 0
    },
    {
      "id": "60b2749c-997b-4b68-a730-175dc0f0284e",
      "title": "PR 1.3: Detalhe + cancelamento (`/notas_fiscais/[id]`)",
      "status": "todo",
      "priority": "high",
      "estimate": "M (4-6h)",
      "labels": [
        "day1",
        "notas"
      ],
      "dependencies": [
        "PR 1.2"
      ],
      "description": "🆕 PRÓXIMO. Spec: `V1-FUNCIONALIDADES.md` §3.5 + PRD §10.1.\n\nArquivos: `app/(auth)/notas_fiscais/[id]/page.tsx`, `[id]/CancelarButton.tsx` (client → `<PopupConfirm>`), `notas_fiscais/actions.ts` (`cancelarNotaAction(id, justificativa)`).\n\n`cancelarNotaAction`: valida `justificativa.length >= 15` (regra SEFAZ) → `focus.cancelarNfe(nota.ref, justificativa, env)` por `nota.tipo_nf` → PATCH `status='cancelada'`, `cancelled_at`, `cancellation_reason` → `revalidatePath('/notas_fiscais')`. Reusa `<PopupConfirm variant='destructive' busy>`, `focus.baixarDanfe`, `focus.baixarXmlNfe`, `focus.cancelarNfe`.\n\nDoD:\n- [ ] Header mostra chave de acesso, protocolo, status\n- [ ] Botões \"Baixar XML\" e \"Baixar DANFE\" funcionam (server action → Focus → binário)\n- [ ] Botão \"Cancelar\" só aparece se `status='ativa'` e (NFS-e) `cancelamento_so_portal=false`\n- [ ] Cancelamento exige justificativa ≥ 15 chars; rejeita se menor\n- [ ] Cancelamento bem-sucedido atualiza `status` na lista (revalidate)",
      "checklist": [
        {
          "text": "Header mostra chave de acesso, protocolo, status",
          "checked": false
        },
        {
          "text": "Botões \"Baixar XML\" e \"Baixar DANFE\" funcionam (server action → Focus → binário)",
          "checked": false
        },
        {
          "text": "Botão \"Cancelar\" só aparece se `status='ativa'` e (NFS-e) `cancelamento_so_portal=false`",
          "checked": false
        },
        {
          "text": "Cancelamento exige justificativa ≥ 15 chars; rejeita se menor",
          "checked": false
        },
        {
          "text": "Cancelamento bem-sucedido atualiza `status` na lista (revalidate)",
          "checked": false
        }
      ],
      "createdAt": "2026-05-25T14:48:34.226604+00:00",
      "updatedAt": "2026-05-25T14:56:19.802307+00:00",
      "order": 1
    },
    {
      "id": "0218026a-9e84-4cf1-bb96-78cc165b9e20",
      "title": "PR 2.1: Form de emissão NFS-e",
      "status": "todo",
      "priority": "high",
      "estimate": "L (6-8h)",
      "labels": [
        "day2",
        "emissao"
      ],
      "dependencies": [
        "PR 1.2"
      ],
      "description": "Spec: `V1-FUNCIONALIDADES.md` §3.1 + PRD §10.2 (variante NFS-e).\n\nArquivos: `app/(auth)/notas_fiscais/emissao/page.tsx` (server: carrega clientes + `empresas_fiscais`), `emissao/EmissaoForm.tsx` (client, Zod), `notas_fiscais/actions.ts` (`emitirNotaAction`). Form: cliente (autocomplete ou consumidor não identificado), descrição, valor (R$ máscara), código ISS (LC 116 top-20 + \"Outro\"). Restante puxado de `empresas_fiscais`.\n\n`emitirNotaAction`: valida Zod → exige `empresa_fiscal_ativada=true` → `ref = focus.generateRef` → insere `notas_fiscais` `status='pendente'` → monta payload NFS-e → `focus.emitirNfse(ref, payload, env)` (`env` de `emitir_nota_homol_antes_producao`) → sucesso: `status='ativa'` + chave/protocolo/links; erro: `status='erro'` + resposta Focus → `revalidatePath` + redirect detalhe. Usar `useActionState` (React 19).\n\nDoD:\n- [ ] Form valida client-side (Zod) — obrigatórios marcados\n- [ ] Botão \"Emitir\" desabilitado se empresa não ativada\n- [ ] Submit chama Focus sandbox; nota aparece com status `ativa` ou `erro`\n- [ ] Erro: toast vermelho com mensagem traduzida (não `rejection_code: 401`)\n- [ ] Webhook `app/api/webhooks/focus/route.ts` recebe callback e atualiza nota (testar via curl)",
      "checklist": [
        {
          "text": "Form valida client-side (Zod) — obrigatórios marcados",
          "checked": false
        },
        {
          "text": "Botão \"Emitir\" desabilitado se empresa não ativada",
          "checked": false
        },
        {
          "text": "Submit chama Focus sandbox; nota aparece com status `ativa` ou `erro`",
          "checked": false
        },
        {
          "text": "Erro: toast vermelho com mensagem traduzida (não `rejection_code: 401`)",
          "checked": false
        },
        {
          "text": "Webhook `app/api/webhooks/focus/route.ts` recebe callback e atualiza nota (testar via curl)",
          "checked": false
        }
      ],
      "createdAt": "2026-05-25T14:48:34.226604+00:00",
      "updatedAt": "2026-05-25T14:56:19.802307+00:00",
      "order": 2
    },
    {
      "id": "f7db9186-a612-417a-ba03-2c6926d4d45f",
      "title": "PR 2.2: Botão \"Emitir nova\" na listagem",
      "status": "todo",
      "priority": "medium",
      "estimate": "S (<1h)",
      "labels": [
        "day2",
        "emissao"
      ],
      "dependencies": [
        "PR 1.2",
        "PR 2.1"
      ],
      "description": "Arquivos: `app/(auth)/notas_fiscais/page.tsx` — adicionar `<Link href=\"/notas_fiscais/emissao\">Emitir nova</Link>` no topo.\n\nDoD:\n- [ ] Botão visível e linka corretamente",
      "checklist": [
        {
          "text": "Botão visível e linka corretamente",
          "checked": false
        }
      ],
      "createdAt": "2026-05-25T14:48:34.226604+00:00",
      "updatedAt": "2026-05-25T14:56:19.802307+00:00",
      "order": 3
    },
    {
      "id": "44d55ef0-1b25-4a40-bea4-8f50ee5b09f7",
      "title": "PR 3.1: Dashboard de impostos (`/impostos`)",
      "status": "todo",
      "priority": "high",
      "estimate": "M (4-6h)",
      "labels": [
        "day3",
        "impostos"
      ],
      "dependencies": [],
      "description": "Spec: `V1-FUNCIONALIDADES.md` §4 + PRD §11.1.\n\nArquivos: `app/(auth)/impostos/page.tsx`, `impostos/ImpostosLayout.tsx` (client, 3 seções: competência atual, histórico de guias, declarações). Queries por `competencia = ${YYYY}${MM}`. `<GuiaCard>`: valor, vencimento, status (badge), botões \"Baixar PDF\", \"Pagar via Pix\" (linha digitável + QR), \"Marcar como paga\". `marcarGuiaPagaAction(id)` → PATCH `status='paga'`, `data_pagamento`.\n\nDoD:\n- [ ] Página carrega sem erro mesmo sem dados (empty state)\n- [ ] Card \"competência atual\" mostra apuração + declaração + guia (ou \"não calculado\" com CTA)\n- [ ] Histórico paginado / scrollable\n- [ ] Toggle guia paga funciona",
      "checklist": [
        {
          "text": "Página carrega sem erro mesmo sem dados (empty state)",
          "checked": false
        },
        {
          "text": "Card \"competência atual\" mostra apuração + declaração + guia (ou \"não calculado\" com CTA)",
          "checked": false
        },
        {
          "text": "Histórico paginado / scrollable",
          "checked": false
        },
        {
          "text": "Toggle guia paga funciona",
          "checked": false
        }
      ],
      "createdAt": "2026-05-25T14:48:34.226604+00:00",
      "updatedAt": "2026-05-25T14:56:19.802307+00:00",
      "order": 4
    },
    {
      "id": "ecf53346-6f3c-492d-a3e2-31e35066acf8",
      "title": "PR 3.2: Cálculo manual — wizard (`/impostos/novo`)",
      "status": "todo",
      "priority": "high",
      "estimate": "L (6-8h)",
      "labels": [
        "day3",
        "impostos",
        "wizard"
      ],
      "dependencies": [
        "PR 3.1"
      ],
      "description": "Spec: `V1-FUNCIONALIDADES.md` §4.1 + §4.2 + PRD §11.2.\n\nArquivos: `app/(auth)/impostos/novo/page.tsx`, `novo/ApuracaoWizard.tsx` (client, 4 etapas), `impostos/actions.ts` (`iniciarApuracaoAction`, `gerarGuiaAction`). Etapas: (1) competência (default mês anterior), (2) consolidar receitas via `n8n.consolidarReceitas` (aguarda webhook/polling), (3) calcular RBT12 + alíquota via `n8n.calcularRbt12` (breakdown), (4) gerar DAS via `serpro.emitirDas`.\n\n`gerarGuiaAction`: busca `empresas_fiscais` + `apuracoes_fiscais` → `serpro.buildEnvelope({...idServico: GERAR_DAS, dados:{pa, valorTotalPago}})` → `serpro.emitirDas(env, envelope)` → persiste `guias_fiscais` com PDF + status `gerada`. Reusa `<Loading>`, padrão `<CreateCompanyDialog>`.\n\nDoD:\n- [ ] Wizard completo das 4 etapas roda no sandbox Serpro\n- [ ] Guia aparece em `/impostos` ao final\n- [ ] Erros em qualquer etapa mostram toast + permitem retry",
      "checklist": [
        {
          "text": "Wizard completo das 4 etapas roda no sandbox Serpro",
          "checked": false
        },
        {
          "text": "Guia aparece em `/impostos` ao final",
          "checked": false
        },
        {
          "text": "Erros em qualquer etapa mostram toast + permitem retry",
          "checked": false
        }
      ],
      "createdAt": "2026-05-25T14:48:34.226604+00:00",
      "updatedAt": "2026-05-25T14:56:19.802307+00:00",
      "order": 5
    },
    {
      "id": "4a1af89a-ccea-4596-bfc9-700864a15caa",
      "title": "PR 3.3: Cron mensal (Vercel Cron)",
      "status": "todo",
      "priority": "medium",
      "estimate": "S (1-2h)",
      "labels": [
        "day3",
        "cron"
      ],
      "dependencies": [
        "PR 3.2"
      ],
      "description": "Spec: `V1-FUNCIONALIDADES.md` §4.1 (automação).\n\nArquivos: `app/api/cron/apuracao-mensal/route.ts` (GET, protegido por `Authorization: Bearer ${CRON_SECRET}`), `vercel.json` (`crons: [{ path, schedule: '0 6 1 * *' }]` = dia 1, 06:00 UTC). Handler: valida header → lista `empresas_fiscais` ativas → invoca `n8n.consolidarReceitas` (fire-and-forget) → log estruturado.\n\nDoD:\n- [ ] Rota protegida (sem header → 401)\n- [ ] Dispara N webhooks n8n em paralelo\n- [ ] Log mostra resultado de cada disparo",
      "checklist": [
        {
          "text": "Rota protegida (sem header → 401)",
          "checked": false
        },
        {
          "text": "Dispara N webhooks n8n em paralelo",
          "checked": false
        },
        {
          "text": "Log mostra resultado de cada disparo",
          "checked": false
        }
      ],
      "createdAt": "2026-05-25T14:48:34.226604+00:00",
      "updatedAt": "2026-05-25T14:56:19.802307+00:00",
      "order": 6
    },
    {
      "id": "4bc34186-3487-4731-a4d1-0d5011d803e4",
      "title": "PR 4.1: Testes E2E do fluxo principal",
      "status": "todo",
      "priority": "high",
      "estimate": "L (6-8h)",
      "labels": [
        "day4",
        "tests",
        "e2e"
      ],
      "dependencies": [
        "PR 1.3",
        "PR 2.1",
        "PR 3.2"
      ],
      "description": "Arquivos: `tests/e2e-fluxo-completo.spec.ts` (novo). Cenário: cadastrar usuário (fixture `service_role`) → login → criar empresa (CNPJ sandbox + ViaCEP) → cadastrar cliente → emitir NFS-e (Focus sandbox) → ver nota → abrir detalhe (chave + DANFE) → wizard `/impostos/novo` até gerar DAS → marcar guia paga → dashboard com receita atualizada. Reusa `tests/smoke.spec.ts` e `walkthrough.spec.ts` como templates.\n\nDoD:\n- [ ] Spec roda do início ao fim sem flakiness\n- [ ] Screenshots salvos em `screenshots/e2e/`\n- [ ] CI-ready (sem interação manual)",
      "checklist": [
        {
          "text": "Spec roda do início ao fim sem flakiness",
          "checked": false
        },
        {
          "text": "Screenshots salvos em `screenshots/e2e/`",
          "checked": false
        },
        {
          "text": "CI-ready (sem interação manual)",
          "checked": false
        }
      ],
      "createdAt": "2026-05-25T14:48:34.226604+00:00",
      "updatedAt": "2026-05-25T14:56:19.802307+00:00",
      "order": 7
    },
    {
      "id": "d09e237d-2168-4f6f-8a2a-4e86535dd291",
      "title": "PR 4.2: Refinar UX",
      "status": "todo",
      "priority": "medium",
      "estimate": "M (3-5h)",
      "labels": [
        "day4",
        "ux",
        "polish"
      ],
      "dependencies": [
        "PR 1.3",
        "PR 3.1"
      ],
      "description": "Empty states em todas as listas (com CTA), mensagens de erro traduzidas (Focus/Serpro → pt-BR humano), loading states (`<Loading fullscreen>`) em server actions longas, sidebar mobile (hamburguer + drawer).\n\nDoD:\n- [ ] Nenhuma página mostra dados crus (\"undefined\", \"[object Object]\")\n- [ ] Mobile (390×844) usa todas as rotas sem overflow horizontal",
      "checklist": [
        {
          "text": "Nenhuma página mostra dados crus (\"undefined\", \"[object Object]\")",
          "checked": false
        },
        {
          "text": "Mobile (390×844) usa todas as rotas sem overflow horizontal",
          "checked": false
        }
      ],
      "createdAt": "2026-05-25T14:48:34.226604+00:00",
      "updatedAt": "2026-05-25T14:56:19.802307+00:00",
      "order": 8
    },
    {
      "id": "45017bed-aa05-4aea-9c43-362692a8f0c3",
      "title": "PR 4.3: Atualizar `README.md`",
      "status": "todo",
      "priority": "low",
      "estimate": "S (1-2h)",
      "labels": [
        "day4",
        "docs"
      ],
      "dependencies": [
        "PR 4.1"
      ],
      "description": "Marcar v1 como \"completa\" na §4. Adicionar §10 \"Como subir em produção\": aplicar migration no Supabase prod, criar bucket `company-certificates` privado, configurar Vercel env vars (todas do `.env.example`), configurar Vercel Cron, apontar domínio, smoke manual de cada rota. Bonus: `ARCHITECTURE.md` com diagrama mermaid `flowchart TD` (browser → Next → Supabase + Focus + Serpro + n8n).\n\nDoD:\n- [ ] §4 marca v1 como completa\n- [ ] §10 deploy prod com checklist escrito\n- [ ] (bonus) ARCHITECTURE.md com diagrama",
      "checklist": [
        {
          "text": "§4 marca v1 como completa",
          "checked": false
        },
        {
          "text": "§10 deploy prod com checklist escrito",
          "checked": false
        },
        {
          "text": "(bonus) ARCHITECTURE.md com diagrama",
          "checked": false
        }
      ],
      "createdAt": "2026-05-25T14:48:34.226604+00:00",
      "updatedAt": "2026-05-25T14:56:19.802307+00:00",
      "order": 9
    },
    {
      "id": "f96857de-5f7c-4620-97a1-79a3f96163e1",
      "title": "PR 4.4: Regerar zip de entrega",
      "status": "todo",
      "priority": "low",
      "estimate": "S (<1h)",
      "labels": [
        "day4",
        "handoff"
      ],
      "dependencies": [
        "PR 4.1",
        "PR 4.2",
        "PR 4.3"
      ],
      "description": "Regerar `balu.zip` excluindo `node_modules`, `.next`, `.env.local`, `playwright-report`, `test-results`, `*.DS_Store`. Conferir conteúdo com `unzip -l`.\n\nDoD:\n- [ ] Zip gerado sem artefatos pesados/secretos\n- [ ] `unzip -l` confere conteúdo esperado",
      "checklist": [
        {
          "text": "Zip gerado sem artefatos pesados/secretos",
          "checked": false
        },
        {
          "text": "`unzip -l` confere conteúdo esperado",
          "checked": false
        }
      ],
      "createdAt": "2026-05-25T14:48:34.226604+00:00",
      "updatedAt": "2026-05-25T14:56:19.802307+00:00",
      "order": 10
    },
    {
      "id": "2a06f614-49f1-4669-94e5-2620f26370df",
      "createdAt": "2026-05-25T20:46:39.391288+00:00",
      "order": 2,
      "title": "Auth: Tipo de conta + confirmação de senha (`/cadastro`)",
      "status": "done",
      "priority": "medium",
      "estimate": "S",
      "labels": [
        "auth",
        "cadastro"
      ],
      "dependencies": [],
      "description": "Melhorias no cadastro de usuário (fora dos PRs numerados do plano).\n\n- Dropdown \"Tipo de conta\" com valores `Empresa`/`Contador` (+ placeholder vazio).\n- Campo \"Confirmar senha\" com validação client-side (`handleSubmit`) e server-side (`signupAction`).\n- `signupAction` envia o tipo no metadata sob a chave `type`.\n- Trigger `handle_new_user_role` (migration `0002`) lê `raw_user_meta_data->>'type'` e cria o registro em `role_types` (default `Empresa`).\n\nCommits: `1594e50`, `4df6899`.\n\n**Pendente**: aplicar a migration `0002` no Supabase hospedado para o trigger existir no banco.",
      "checklist": [
        {
          "text": "Dropdown \"Tipo de conta\" (Empresa/Contador) no /cadastro",
          "checked": true
        },
        {
          "text": "Campo \"Confirmar senha\" + validação (client + server)",
          "checked": true
        },
        {
          "text": "signupAction envia `type` no metadata",
          "checked": true
        },
        {
          "text": "Trigger handle_new_user_role (0002) → role_types",
          "checked": true
        },
        {
          "text": "Aplicar 0002 no Supabase hospedado",
          "checked": false
        }
      ],
      "updatedAt": "2026-05-25T20:46:39.391288+00:00"
    },
    {
      "id": "e87f3040-755d-41ee-a2db-8033efdb8335",
      "title": "Reconciliação schema código↔banco (Passo 0/1/1.5)",
      "status": "done",
      "priority": "Alta",
      "estimate": "",
      "labels": [
        "db",
        "reconciliação"
      ],
      "dependencies": [],
      "description": "Migrations 0001/0002 + types descreviam schema idealizado (Bubble/PRD) nunca aplicado. Banco real (PG 17.6, motor n8n) é a fonte da verdade. Alinhado o código ao banco. Ver `DB-DIVERGENCIA.md`.",
      "checklist": [
        {
          "text": "Diff completo via pg_dump documentado (DB-DIVERGENCIA.md)",
          "checked": true
        },
        {
          "text": "types/database.ts regenerado do banco real",
          "checked": true
        },
        {
          "text": "Dashboard queries + notas alinhados (commit 8929d2c)",
          "checked": true
        },
        {
          "text": "Auth/onboarding/profile alinhados (commit 92e12fd)",
          "checked": true
        },
        {
          "text": "E2E validado no browser (cadastro→dashboard→notas→clientes)",
          "checked": true
        },
        {
          "text": "Passo 2: migration 0003 aditivo (cols notas p/ emissão/cancelamento)",
          "checked": false
        },
        {
          "text": "Passo 3: apuração/DAS no formato real",
          "checked": false
        },
        {
          "text": "Passo 4: versionar user_types/role_types/receitas_fiscais + corrigir RPC no banco",
          "checked": false
        }
      ],
      "createdAt": "2026-05-26T19:16:54.000Z",
      "updatedAt": "2026-05-26T19:16:54.000Z",
      "order": 11
    }
  ]
}